logrouter/__init__.py
logrouter/default_logging_conf.yaml
logrouter/logrouter.py
logrouter/setup_logging.py
logrouter-0.0.2.dist-info/METADATA
logrouter-0.0.2.dist-info/WHEEL
logrouter-0.0.2.dist-info/licenses/LICENSE
logrouter-0.0.2.dist-info/RECORD
