Metadata-Version: 2.1
Name: logrouter
Version: 0.0.2
Summary: A package that allows logs to be routed to different handlers based on a discriminant
Author-email: Martín Santillán Cooper <msantillancooper@ibm.com>
License-File: LICENSE
Classifier: License :: OSI Approved :: MIT License
Classifier: Operating System :: OS Independent
Classifier: Programming Language :: Python :: 3
Requires-Python: >=3.7
Requires-Dist: pyyaml
